starkiller/__init__.py
starkiller/models.py
starkiller/names_scanner.py
starkiller/parsing.py
starkiller/project.py
starkiller/refactoring.py
starkiller/utils.py
starkiller/pylsp_plugin/__init__.py
starkiller/pylsp_plugin/plugin.py
starkiller-0.1.3.dist-info/METADATA
starkiller-0.1.3.dist-info/WHEEL
starkiller-0.1.3.dist-info/entry_points.txt
starkiller-0.1.3.dist-info/licenses/LICENSE
starkiller-0.1.3.dist-info/RECORD
