Metadata-Version: 2.4
Name: starkiller
Version: 0.1.3
Summary: Import refactoring package and pylsp plugin
Project-URL: Homepage, https://github.com/kompoth/starkiller
License-File: LICENSE
Classifier: Development Status :: 3 - Alpha
Classifier: Environment :: Plugins
Classifier: Intended Audience :: Developers
Classifier: License :: OSI Approved :: MIT License
Classifier: Operating System :: OS Independent
Classifier: Programming Language :: Python
Classifier: Programming Language :: Python :: 3 :: Only
Classifier: Programming Language :: Python :: 3.12
Classifier: Programming Language :: Python :: 3.13
Classifier: Topic :: Software Development
Classifier: Topic :: Software Development :: Code Generators
Classifier: Typing :: Typed
Requires-Python: >=3.12
Requires-Dist: jedi>=0.19.2
Provides-Extra: pylsp
Requires-Dist: lsprotocol>=2023.0.1; extra == 'pylsp'
Requires-Dist: python-lsp-server>=1.12.2; extra == 'pylsp'
